nueva/__init__.py
nueva-0.0.0.dist-info/METADATA
nueva-0.0.0.dist-info/WHEEL
nueva-0.0.0.dist-info/top_level.txt
nueva-0.0.0.dist-info/RECORD
