Metadata-Version: 2.1
Name: nueva
Version: 0.0.0
Summary: Nueva
Home-page: UNKNOWN
License: UNKNOWN
Platform: UNKNOWN
Classifier: Programming Language :: Python :: 3.9
Requires-Dist: ravel
Requires-Dist: appyratus
Requires-Dist: pytest
Requires-Dist: ipdb
